faresadd/__init__.py
faresadd/add.py
faresadd-1.1.dist-info/LICENSE
faresadd-1.1.dist-info/METADATA
faresadd-1.1.dist-info/WHEEL
faresadd-1.1.dist-info/top_level.txt
faresadd-1.1.dist-info/RECORD
