Metadata-Version: 2.1
Name: faresadd
Version: 1.1
Summary: A package from me to add and sub easy 
License-File: LICENSE
